{
  "z": 3,
  "x": 7,
  "y": 3,
  "bounds": {
    "west": 135,
    "south": 0,
    "east": 180,
    "north": 22.5
  },
  "grid": {
    "width": 32,
    "height": 32
  },
  "minElevationMeters": -858,
  "maxElevationMeters": 2068,
  "encoding": "heightmap-json-v1",
  "values": [
    [
      85,
      128,
      170,
      238,
      317,
      398,
      508,
      617,
      503,
      162,
      -179,
      232,
      741,
      1051,
      835,
      619,
      460,
      330,
      218,
      417,
      617,
      547,
      135,
      -276,
      -5,
      404,
      661,
      380,
      99,
      189,
      515,
      842
    ],
    [
      -10,
      97,
      203,
      294,
      379,
      464,
      545,
      627,
      507,
      181,
      -145,
      225,
      686,
      932,
      604,
      276,
      207,
      270,
      335,
      455,
      574,
      454,
      32,
      -390,
      -123,
      284,
      572,
      442,
      313,
      447,
      749,
      1051
    ],
    [
      -100,
      67,
      233,
      346,
      438,
      526,
      580,
      635,
      509,
      198,
      -112,
      219,
      634,
      816,
      380,
      -56,
      -38,
      212,
      451,
      491,
      531,
      362,
      -70,
      -502,
      -239,
      164,
      482,
      502,
      521,
      697,
      972,
      1248
    ],
    [
      11,
      65,
      118,
      222,
      346,
      460,
      484,
      508,
      389,
      123,
      -143,
      219,
      664,
      880,
      490,
      99,
      97,
      292,
      476,
      466,
      456,
      275,
      -122,
      -518,
      -277,
      94,
      392,
      436,
      479,
      579,
      714,
      850
    ],
    [
      122,
      63,
      3,
      98,
      254,
      393,
      387,
      382,
      269,
      47,
      -174,
      220,
      694,
      945,
      600,
      255,
      232,
      372,
      501,
      441,
      382,
      189,
      -173,
      -535,
      -315,
      24,
      303,
      370,
      437,
      461,
      456,
      452
    ],
    [
      233,
      61,
      -112,
      -26,
      162,
      326,
      291,
      255,
      149,
      -28,
      -205,
      220,
      724,
      1009,
      710,
      411,
      367,
      452,
      526,
      417,
      307,
      102,
      -225,
      -552,
      -352,
      -46,
      213,
      304,
      396,
      343,
      199,
      54
    ],
    [
      344,
      59,
      -227,
      -150,
      69,
      259,
      194,
      129,
      30,
      -103,
      -237,
      220,
      755,
      1074,
      820,
      567,
      502,
      532,
      552,
      392,
      233,
      15,
      -277,
      -569,
      -390,
      -116,
      123,
      238,
      354,
      225,
      -59,
      -344
    ],
    [
      454,
      57,
      -341,
      -274,
      -23,
      192,
      97,
      2,
      -90,
      -179,
      -268,
      221,
      785,
      1138,
      931,
      723,
      637,
      612,
      577,
      368,
      159,
      -72,
      -329,
      -586,
      -428,
      -186,
      33,
      173,
      312,
      107,
      -317,
      -741
    ],
    [
      373,
      -24,
      -420,
      -338,
      -66,
      169,
      89,
      9,
      -87,
      -197,
      -307,
      183,
      753,
      1107,
      890,
      673,
      566,
      516,
      462,
      338,
      215,
      32,
      -226,
      -484,
      -378,
      -198,
      -28,
      110,
      248,
      37,
      -398,
      -833
    ],
    [
      225,
      -130,
      -486,
      -380,
      -91,
      162,
      111,
      61,
      -41,
      -195,
      -349,
      133,
      699,
      1042,
      797,
      552,
      425,
      360,
      299,
      307,
      316,
      201,
      -70,
      -341,
      -298,
      -190,
      -78,
      49,
      177,
      -18,
      -419,
      -820
    ],
    [
      77,
      -237,
      -551,
      -422,
      -117,
      154,
      133,
      113,
      4,
      -193,
      -391,
      83,
      645,
      978,
      704,
      430,
      285,
      204,
      135,
      276,
      417,
      369,
      85,
      -199,
      -217,
      -182,
      -129,
      -12,
      106,
      -72,
      -439,
      -806
    ],
    [
      -71,
      -344,
      -617,
      -465,
      -143,
      147,
      156,
      165,
      50,
      -192,
      -433,
      33,
      591,
      914,
      611,
      309,
      144,
      48,
      -28,
      245,
      517,
      538,
      241,
      -56,
      -137,
      -175,
      -180,
      -73,
      34,
      -127,
      -460,
      -793
    ],
    [
      -219,
      -451,
      -683,
      -507,
      -168,
      139,
      178,
      217,
      95,
      -190,
      -475,
      -18,
      537,
      850,
      519,
      188,
      3,
      -108,
      -191,
      214,
      618,
      707,
      397,
      87,
      -57,
      -167,
      -231,
      -134,
      -37,
      -181,
      -480,
      -779
    ],
    [
      -291,
      -485,
      -679,
      -507,
      -189,
      101,
      152,
      204,
      104,
      -151,
      -405,
      2,
      496,
      764,
      431,
      98,
      -80,
      -180,
      -250,
      203,
      656,
      776,
      476,
      176,
      9,
      -132,
      -224,
      -148,
      -71,
      -193,
      -442,
      -690
    ],
    [
      -277,
      -437,
      -597,
      -460,
      -205,
      28,
      73,
      117,
      71,
      -69,
      -209,
      101,
      471,
      655,
      349,
      43,
      -99,
      -157,
      -190,
      215,
      621,
      731,
      469,
      206,
      59,
      -66,
      -153,
      -109,
      -64,
      -157,
      -336,
      -516
    ],
    [
      -262,
      -388,
      -514,
      -412,
      -220,
      -45,
      -7,
      31,
      37,
      12,
      -13,
      200,
      445,
      546,
      267,
      -12,
      -117,
      -134,
      -130,
      228,
      586,
      686,
      461,
      236,
      108,
      1,
      -81,
      -69,
      -58,
      -120,
      -231,
      -341
    ],
    [
      -248,
      -339,
      -431,
      -365,
      -236,
      -118,
      -87,
      -56,
      4,
      93,
      183,
      299,
      419,
      437,
      185,
      -67,
      -135,
      -110,
      -70,
      240,
      551,
      642,
      454,
      266,
      158,
      67,
      -9,
      -30,
      -51,
      -84,
      -125,
      -167
    ],
    [
      -233,
      -291,
      -348,
      -318,
      -252,
      -190,
      -166,
      -142,
      -29,
      175,
      379,
      398,
      393,
      328,
      103,
      -122,
      -154,
      -87,
      -11,
      253,
      516,
      597,
      446,
      295,
      208,
      133,
      63,
      9,
      -44,
      -47,
      -20,
      8
    ],
    [
      -231,
      -267,
      -303,
      -297,
      -275,
      -252,
      -223,
      -193,
      -32,
      264,
      560,
      503,
      401,
      274,
      82,
      -110,
      -122,
      -44,
      41,
      256,
      471,
      549,
      452,
      356,
      269,
      184,
      104,
      43,
      -19,
      16,
      115,
      213
    ],
    [
      -277,
      -345,
      -414,
      -391,
      -331,
      -269,
      -180,
      -92,
      96,
      386,
      676,
      634,
      550,
      452,
      320,
      189,
      121,
      85,
      60,
      221,
      382,
      486,
      516,
      546,
      380,
      175,
      21,
      50,
      79,
      196,
      371,
      545
    ],
    [
      -323,
      -424,
      -525,
      -484,
      -387,
      -285,
      -138,
      10,
      225,
      508,
      791,
      765,
      699,
      631,
      559,
      487,
      363,
      214,
      78,
      186,
      294,
      423,
      579,
      735,
      491,
      165,
      -62,
      57,
      176,
      376,
      627,
      878
    ],
    [
      -370,
      -503,
      -636,
      -578,
      -444,
      -302,
      -95,
      111,
      353,
      630,
      907,
      896,
      848,
      809,
      797,
      785,
      606,
      343,
      97,
      151,
      205,
      360,
      642,
      925,
      602,
      155,
      -146,
      64,
      274,
      556,
      883,
      1210
    ],
    [
      -416,
      -581,
      -747,
      -671,
      -500,
      -318,
      -53,
      213,
      481,
      752,
      1023,
      1027,
      997,
      988,
      1035,
      1083,
      849,
      472,
      115,
      115,
      116,
      297,
      706,
      1115,
      713,
      146,
      -229,
      72,
      372,
      736,
      1139,
      1543
    ],
    [
      -462,
      -660,
      -858,
      -764,
      -556,
      -335,
      -10,
      314,
      609,
      874,
      1139,
      1158,
      1146,
      1167,
      1274,
      1381,
      1092,
      601,
      133,
      80,
      27,
      234,
      769,
      1305,
      823,
      136,
      -313,
      79,
      470,
      916,
      1396,
      1876
    ],
    [
      -315,
      -586,
      -857,
      -766,
      -531,
      -292,
      -10,
      271,
      555,
      840,
      1124,
      1088,
      1010,
      998,
      1162,
      1326,
      1158,
      823,
      495,
      298,
      102,
      240,
      803,
      1365,
      926,
      283,
      -152,
      145,
      441,
      802,
      1204,
      1606
    ],
    [
      -149,
      -497,
      -845,
      -759,
      -500,
      -243,
      -14,
      216,
      484,
      791,
      1098,
      999,
      847,
      796,
      1017,
      1238,
      1209,
      1053,
      888,
      540,
      191,
      254,
      833,
      1413,
      1027,
      445,
      32,
      216,
      400,
      661,
      971,
      1281
    ],
    [
      17,
      -409,
      -834,
      -752,
      -468,
      -195,
      -18,
      160,
      412,
      742,
      1072,
      910,
      683,
      595,
      872,
      1150,
      1259,
      1284,
      1281,
      781,
      281,
      267,
      864,
      1462,
      1128,
      606,
      216,
      287,
      359,
      520,
      737,
      955
    ],
    [
      182,
      -320,
      -823,
      -745,
      -436,
      -146,
      -21,
      104,
      341,
      693,
      1045,
      821,
      520,
      394,
      728,
      1061,
      1310,
      1515,
      1674,
      1023,
      371,
      280,
      895,
      1510,
      1229,
      768,
      399,
      359,
      318,
      379,
      504,
      629
    ],
    [
      348,
      -232,
      -811,
      -737,
      -404,
      -98,
      -25,
      48,
      270,
      645,
      1019,
      732,
      357,
      192,
      583,
      973,
      1360,
      1745,
      2068,
      1264,
      461,
      293,
      925,
      1558,
      1331,
      929,
      583,
      430,
      277,
      238,
      271,
      304
    ],
    [
      397,
      -192,
      -781,
      -680,
      -306,
      32,
      55,
      78,
      244,
      558,
      871,
      584,
      218,
      63,
      470,
      877,
      1254,
      1616,
      1921,
      1205,
      489,
      366,
      992,
      1619,
      1398,
      1006,
      669,
      529,
      390,
      320,
      296,
      271
    ],
    [
      380,
      -179,
      -739,
      -594,
      -170,
      207,
      181,
      156,
      244,
      449,
      654,
      403,
      92,
      -25,
      375,
      775,
      1059,
      1283,
      1469,
      974,
      480,
      473,
      1080,
      1687,
      1446,
      1034,
      700,
      645,
      590,
      530,
      467,
      405
    ],
    [
      364,
      -167,
      -697,
      -508,
      -34,
      382,
      308,
      234,
      244,
      340,
      437,
      222,
      -35,
      -113,
      281,
      674,
      863,
      949,
      1016,
      744,
      472,
      580,
      1168,
      1755,
      1494,
      1062,
      731,
      760,
      789,
      739,
      639,
      538
    ]
  ]
}