{
  "z": 3,
  "x": 5,
  "y": 4,
  "bounds": {
    "west": 45,
    "south": -22.5,
    "east": 90,
    "north": 0
  },
  "grid": {
    "width": 32,
    "height": 32
  },
  "encoding": "heightmap-json-v1",
  "minElevationMeters": -2430,
  "maxElevationMeters": 2524,
  "values": [
    [
      483,
      959,
      1189,
      997,
      806,
      272,
      -372,
      -812,
      -70,
      671,
      776,
      331,
      -113,
      -32,
      92,
      284,
      626,
      969,
      889,
      633,
      442,
      878,
      1315,
      1055,
      54,
      -947,
      -162,
      881,
      1498,
      920,
      342,
      572
    ],
    [
      452,
      1300,
      1767,
      1582,
      1398,
      800,
      71,
      -433,
      365,
      1164,
      1089,
      261,
      -567,
      -598,
      -566,
      -384,
      120,
      625,
      720,
      642,
      620,
      1119,
      1619,
      1306,
      125,
      -1055,
      -179,
      995,
      1643,
      817,
      -9,
      192
    ],
    [
      421,
      1641,
      2346,
      2168,
      1989,
      1328,
      514,
      -54,
      801,
      1656,
      1402,
      191,
      -1020,
      -1164,
      -1223,
      -1053,
      -385,
      282,
      550,
      652,
      797,
      1360,
      1924,
      1556,
      196,
      -1164,
      -195,
      1109,
      1788,
      714,
      -361,
      -187
    ],
    [
      336,
      1717,
      2524,
      2348,
      2173,
      1552,
      789,
      248,
      992,
      1735,
      1368,
      44,
      -1281,
      -1504,
      -1638,
      -1497,
      -757,
      -16,
      314,
      474,
      678,
      1309,
      1940,
      1619,
      284,
      -1051,
      -86,
      1212,
      1867,
      722,
      -423,
      -292
    ],
    [
      154,
      1323,
      1995,
      1816,
      1637,
      1238,
      768,
      417,
      750,
      1083,
      721,
      -240,
      -1202,
      -1443,
      -1626,
      -1544,
      -890,
      -235,
      -39,
      -35,
      35,
      741,
      1448,
      1352,
      401,
      -550,
      246,
      1295,
      1830,
      928,
      25,
      89
    ],
    [
      -27,
      930,
      1466,
      1284,
      1102,
      924,
      747,
      585,
      508,
      431,
      74,
      -524,
      -1123,
      -1382,
      -1613,
      -1592,
      -1023,
      -454,
      -393,
      -544,
      -607,
      174,
      955,
      1084,
      518,
      -49,
      579,
      1378,
      1794,
      1133,
      473,
      469
    ],
    [
      -208,
      536,
      937,
      752,
      567,
      610,
      726,
      754,
      267,
      -220,
      -573,
      -808,
      -1044,
      -1321,
      -1600,
      -1639,
      -1156,
      -673,
      -747,
      -1053,
      -1250,
      -394,
      463,
      816,
      634,
      453,
      911,
      1461,
      1757,
      1339,
      921,
      850
    ],
    [
      -389,
      142,
      408,
      220,
      31,
      296,
      705,
      922,
      25,
      -872,
      -1220,
      -1092,
      -965,
      -1260,
      -1588,
      -1687,
      -1289,
      -892,
      -1100,
      -1562,
      -1892,
      -961,
      -30,
      548,
      751,
      954,
      1243,
      1544,
      1720,
      1544,
      1368,
      1231
    ],
    [
      -515,
      -189,
      -62,
      -275,
      -487,
      -24,
      654,
      1049,
      -199,
      -1447,
      -1776,
      -1314,
      -852,
      -1160,
      -1530,
      -1688,
      -1387,
      -1085,
      -1408,
      -1992,
      -2429,
      -1463,
      -497,
      271,
      828,
      1384,
      1518,
      1590,
      1657,
      1708,
      1759,
      1564
    ],
    [
      -40,
      151,
      101,
      -362,
      -826,
      -413,
      279,
      729,
      -229,
      -1188,
      -1365,
      -870,
      -375,
      -650,
      -987,
      -1189,
      -1098,
      -1007,
      -1224,
      -1569,
      -1827,
      -1256,
      -685,
      -110,
      469,
      1048,
      1176,
      1239,
      1314,
      1423,
      1532,
      1382
    ],
    [
      435,
      491,
      263,
      -450,
      -1164,
      -801,
      -95,
      408,
      -260,
      -929,
      -954,
      -426,
      103,
      -140,
      -444,
      -690,
      -809,
      -929,
      -1039,
      -1146,
      -1226,
      -1049,
      -873,
      -491,
      110,
      711,
      834,
      888,
      972,
      1138,
      1305,
      1200
    ],
    [
      910,
      831,
      426,
      -538,
      -1502,
      -1190,
      -470,
      87,
      -291,
      -670,
      -543,
      19,
      581,
      370,
      99,
      -191,
      -521,
      -851,
      -855,
      -723,
      -624,
      -843,
      -1061,
      -872,
      -249,
      374,
      492,
      537,
      629,
      854,
      1078,
      1019
    ],
    [
      1386,
      1171,
      588,
      -626,
      -1840,
      -1578,
      -845,
      -233,
      -322,
      -410,
      -132,
      463,
      1058,
      881,
      642,
      308,
      -232,
      -772,
      -670,
      -300,
      -23,
      -636,
      -1250,
      -1254,
      -608,
      37,
      150,
      186,
      287,
      569,
      851,
      837
    ],
    [
      1861,
      1511,
      751,
      -714,
      -2178,
      -1967,
      -1220,
      -554,
      -353,
      -151,
      279,
      907,
      1536,
      1391,
      1185,
      807,
      56,
      -694,
      -486,
      123,
      579,
      -429,
      -1438,
      -1635,
      -967,
      -299,
      -192,
      -165,
      -56,
      284,
      624,
      655
    ],
    [
      1536,
      1282,
      635,
      -689,
      -2014,
      -1810,
      -1117,
      -485,
      -200,
      86,
      489,
      993,
      1498,
      1435,
      1327,
      998,
      190,
      -618,
      -422,
      195,
      665,
      -252,
      -1168,
      -1425,
      -977,
      -529,
      -301,
      -105,
      107,
      362,
      617,
      665
    ],
    [
      1021,
      919,
      453,
      -638,
      -1730,
      -1523,
      -902,
      -325,
      -3,
      318,
      651,
      994,
      1337,
      1368,
      1374,
      1116,
      287,
      -543,
      -386,
      182,
      630,
      -81,
      -791,
      -1075,
      -904,
      -734,
      -355,
      53,
      390,
      525,
      661,
      720
    ],
    [
      507,
      556,
      271,
      -588,
      -1446,
      -1237,
      -686,
      -164,
      193,
      550,
      813,
      995,
      1177,
      1301,
      1420,
      1234,
      383,
      -467,
      -350,
      170,
      594,
      90,
      -413,
      -724,
      -832,
      -939,
      -410,
      211,
      673,
      689,
      704,
      775
    ],
    [
      -8,
      193,
      89,
      -537,
      -1163,
      -950,
      -470,
      -3,
      390,
      783,
      976,
      996,
      1016,
      1234,
      1467,
      1352,
      480,
      -392,
      -315,
      158,
      558,
      261,
      -35,
      -374,
      -759,
      -1143,
      -464,
      369,
      956,
      852,
      748,
      830
    ],
    [
      -522,
      -170,
      -93,
      -486,
      -879,
      -664,
      -255,
      157,
      586,
      1015,
      1138,
      997,
      856,
      1167,
      1514,
      1470,
      577,
      -316,
      -279,
      146,
      522,
      433,
      343,
      -24,
      -686,
      -1348,
      -518,
      527,
      1239,
      1016,
      792,
      885
    ],
    [
      -664,
      -231,
      -60,
      -340,
      -620,
      -498,
      -247,
      38,
      525,
      1012,
      1091,
      820,
      548,
      943,
      1391,
      1413,
      514,
      -386,
      -330,
      126,
      527,
      412,
      297,
      -30,
      -582,
      -1133,
      -452,
      408,
      983,
      763,
      542,
      705
    ],
    [
      -479,
      -25,
      162,
      -111,
      -383,
      -438,
      -423,
      -328,
      237,
      801,
      861,
      486,
      110,
      580,
      1117,
      1203,
      310,
      -583,
      -456,
      99,
      568,
      223,
      -123,
      -349,
      -449,
      -550,
      -280,
      44,
      253,
      143,
      32,
      318
    ],
    [
      -293,
      181,
      383,
      118,
      -146,
      -378,
      -599,
      -693,
      -51,
      591,
      631,
      152,
      -328,
      217,
      844,
      993,
      106,
      -781,
      -582,
      72,
      608,
      33,
      -542,
      -668,
      -317,
      34,
      -108,
      -320,
      -477,
      -477,
      -477,
      -69
    ],
    [
      -107,
      387,
      605,
      348,
      91,
      -318,
      -775,
      -1059,
      -339,
      381,
      401,
      -182,
      -766,
      -145,
      571,
      783,
      -98,
      -978,
      -707,
      45,
      649,
      -156,
      -961,
      -987,
      -185,
      618,
      65,
      -684,
      -1207,
      -1097,
      -987,
      -455
    ],
    [
      78,
      593,
      826,
      577,
      328,
      -258,
      -951,
      -1425,
      -627,
      170,
      171,
      -516,
      -1204,
      -508,
      298,
      573,
      -301,
      -1176,
      -833,
      17,
      690,
      -345,
      -1380,
      -1306,
      -52,
      1201,
      237,
      -1049,
      -1938,
      -1717,
      -1497,
      -842
    ],
    [
      220,
      783,
      1046,
      795,
      545,
      -150,
      -987,
      -1583,
      -778,
      27,
      -18,
      -796,
      -1573,
      -805,
      86,
      427,
      -424,
      -1275,
      -889,
      13,
      719,
      -454,
      -1628,
      -1484,
      62,
      1608,
      376,
      -1257,
      -2387,
      -2104,
      -1820,
      -1130
    ],
    [
      233,
      924,
      1258,
      982,
      705,
      97,
      -616,
      -1134,
      -528,
      79,
      -86,
      -915,
      -1745,
      -912,
      53,
      467,
      -311,
      -1089,
      -742,
      76,
      717,
      -329,
      -1375,
      -1249,
      125,
      1499,
      420,
      -1014,
      -2016,
      -1809,
      -1602,
      -1128
    ],
    [
      246,
      1065,
      1471,
      1168,
      865,
      345,
      -244,
      -686,
      -278,
      130,
      -154,
      -1035,
      -1916,
      -1019,
      20,
      508,
      -198,
      -903,
      -594,
      138,
      715,
      -204,
      -1122,
      -1014,
      188,
      1390,
      464,
      -771,
      -1646,
      -1515,
      -1384,
      -1126
    ],
    [
      259,
      1207,
      1684,
      1355,
      1025,
      593,
      128,
      -238,
      -28,
      182,
      -222,
      -1154,
      -2087,
      -1126,
      -13,
      548,
      -85,
      -717,
      -447,
      201,
      712,
      -79,
      -870,
      -779,
      251,
      1281,
      507,
      -527,
      -1275,
      -1220,
      -1165,
      -1123
    ],
    [
      272,
      1348,
      1897,
      1541,
      1185,
      840,
      499,
      210,
      222,
      234,
      -290,
      -1274,
      -2259,
      -1232,
      -46,
      588,
      29,
      -531,
      -299,
      263,
      710,
      46,
      -617,
      -544,
      314,
      1172,
      551,
      -284,
      -904,
      -926,
      -947,
      -1121
    ],
    [
      285,
      1490,
      2109,
      1727,
      1345,
      1088,
      871,
      658,
      472,
      285,
      -357,
      -1394,
      -2430,
      -1339,
      -79,
      629,
      142,
      -345,
      -152,
      326,
      708,
      172,
      -364,
      -309,
      377,
      1063,
      595,
      -40,
      -534,
      -631,
      -728,
      -1119
    ],
    [
      528,
      1520,
      2029,
      1710,
      1390,
      1019,
      630,
      292,
      239,
      187,
      -206,
      -893,
      -1580,
      -849,
      -6,
      487,
      221,
      -45,
      35,
      260,
      421,
      -31,
      -482,
      -333,
      454,
      1241,
      804,
      189,
      -305,
      -464,
      -623,
      -823
    ],
    [
      776,
      1549,
      1943,
      1688,
      1433,
      942,
      377,
      -93,
      -4,
      85,
      -50,
      -379,
      -708,
      -347,
      70,
      342,
      300,
      258,
      223,
      191,
      127,
      -240,
      -607,
      -363,
      531,
      1425,
      1016,
      418,
      -80,
      -300,
      -520,
      -521
    ]
  ]
}