{
  "year": 1519,
  "eraIndex": 1,
  "nextEraIndex": 2,
  "phase": "Research Commonwealth Expansion -> Research Commonwealth Realignment",
  "progress": 0.967266775777414,
  "civilizationStage": "industrial",
  "civilizationStageLabel": "Industrial",
  "builtEnvironmentLevel": 4,
  "detailMode": "street",
  "allowStreetMode": true,
  "branchOverrideReason": "Accelerated learning systems and coordinated institutions pull advanced settlement forms earlier than baseline history.",
  "historyStartYear": -220000,
  "historyEndYear": 1699,
  "historyStartReason": "This branch begins with anatomically early humans and preserves a long prehistory before institutional divergence.",
  "firstSettlementYear": -3800,
  "firstSettlementReason": "The interactive branch timeline begins with the first durable settlements that can support knowledge exchange.",
  "summary": "In 1519, knowledge acceleration is in an industrial stage, with a warmer atmosphere, higher coastlines, 52% vegetation vitality, and 58% settlement intensity relative to the branch baseline.",
  "systems": {
    "atmosphere": {
      "temperatureAnomalyC": 1.07,
      "aerosolIndex": 0.243,
      "cloudCover": 0.491,
      "stormEnergyIndex": 0.655
    },
    "ocean": {
      "seaLevelMeters": 3.74,
      "surfaceTempAnomalyC": 0.66,
      "currentIntensityIndex": 0.693,
      "salinityShiftIndex": 0.036
    },
    "landUse": {
      "cultivatedShare": 0.281,
      "urbanShare": 0.18,
      "restorationShare": 0.169,
      "extractionShare": 0.188
    },
    "vegetation": {
      "vitalityIndex": 0.516,
      "forestCoverShare": 0.434,
      "cropDiversityIndex": 0.283
    },
    "ice": {
      "polarExtentIndex": 0.557,
      "glacierMassIndex": 0.551,
      "albedoIndex": 0.505
    },
    "settlement": {
      "intensityIndex": 0.578,
      "connectivityIndex": 0.446,
      "coastalUrbanShare": 0.166,
      "orbitalInfrastructureIndex": 0.018
    }
  },
  "tiles": {
    "surface": "./processed/history/tiles/1519/surface/0/0/0.svg",
    "climate": "./processed/history/tiles/1519/climate/0/0/0.svg",
    "settlement": "./processed/history/tiles/1519/settlement/0/0/0.svg"
  },
  "render": {
    "year": 1519,
    "globe": {
      "baseColor": "#24496a",
      "atmosphereTint": "#8fd7ff",
      "fogTint": "#6dc7ff",
      "hueShift": -0.007,
      "saturationShift": 0.12,
      "brightnessShift": 0.055,
      "fogDensity": 0.000145,
      "layerStyles": {
        "surface": {
          "alpha": 1,
          "brightness": 1.08,
          "contrast": 1.18,
          "saturation": 1.31,
          "gamma": 0.99,
          "hue": 0
        },
        "elevation": {
          "alpha": 0.32,
          "brightness": 1.04,
          "contrast": 1.12,
          "saturation": 1.02,
          "gamma": 1,
          "hue": 0
        },
        "climate": {
          "alpha": 0.29,
          "brightness": 1.03,
          "contrast": 1.05,
          "saturation": 1.19,
          "gamma": 1,
          "hue": -0.004
        },
        "biomes": {
          "alpha": 0.3,
          "brightness": 1.02,
          "contrast": 1.08,
          "saturation": 1.25,
          "gamma": 1,
          "hue": -0.003
        },
        "hydrology": {
          "alpha": 0.42,
          "brightness": 1.06,
          "contrast": 1.12,
          "saturation": 1.23,
          "gamma": 1,
          "hue": -0.02
        },
        "settlement": {
          "alpha": 0.32,
          "brightness": 1.14,
          "contrast": 1.19,
          "saturation": 1.23,
          "gamma": 0.99,
          "hue": -0.005
        }
      }
    },
    "local": {
      "accent": "#93d5ee",
      "road": "#a7cce4",
      "hub": "#f9eeb9",
      "facade": "#9ac9ee",
      "roof": "#dff1fc",
      "parcel": "#45658d",
      "plaza": "#e3e9e7",
      "water": "#6fc2ff",
      "greenery": "#73d1a7",
      "transit": "#9feff9",
      "landmark": "#fef2b9",
      "glow": 0.283,
      "roadGlow": 0.22,
      "buildingAlpha": 0.453,
      "infrastructureMix": 0.213,
      "sceneMood": "By 1559, the branch has fully reorganized its cities around knowledge acceleration."
    }
  }
}